odoo/addons/stock_location_limit_product/README.rst
odoo/addons/stock_location_limit_product/__init__.py
odoo/addons/stock_location_limit_product/__manifest__.py
odoo/addons/stock_location_limit_product/i18n/es.po
odoo/addons/stock_location_limit_product/i18n/stock_location_limit_product.pot
odoo/addons/stock_location_limit_product/models/__init__.py
odoo/addons/stock_location_limit_product/models/product_template.py
odoo/addons/stock_location_limit_product/models/stock_location.py
odoo/addons/stock_location_limit_product/models/stock_location_limit.py
odoo/addons/stock_location_limit_product/readme/CONFIGURE.rst
odoo/addons/stock_location_limit_product/readme/CONTRIBUTORS.rst
odoo/addons/stock_location_limit_product/readme/DESCRIPTION.rst
odoo/addons/stock_location_limit_product/readme/USAGE.rst
odoo/addons/stock_location_limit_product/security/ir.model.access.csv
odoo/addons/stock_location_limit_product/static/description/icon.png
odoo/addons/stock_location_limit_product/static/description/index.html
odoo/addons/stock_location_limit_product/tests/__init__.py
odoo/addons/stock_location_limit_product/tests/test_stock_location_limit_product.py
odoo/addons/stock_location_limit_product/views/product_template.xml
odoo/addons/stock_location_limit_product/views/stock_location_view.xml
odoo12_addon_stock_location_limit_product-12.0.1.3.0.dist-info/METADATA
odoo12_addon_stock_location_limit_product-12.0.1.3.0.dist-info/WHEEL
odoo12_addon_stock_location_limit_product-12.0.1.3.0.dist-info/top_level.txt
odoo12_addon_stock_location_limit_product-12.0.1.3.0.dist-info/RECORD
