Metadata-Version: 2.1
Name: odoo12-addon-stock-location-limit-product
Version: 12.0.1.3.0
Summary: Add a limit by product quantity on a stock location. This limit can later be used to track the capacity available of the location.
Home-page: https://github.com/OCA/stock-logistics-warehouse
Author: Open Source Integrators, Odoo Community Association (OCA),
Author-email: support@odoo-community.org
License: AGPL-3
Platform: UNKNOWN
Classifier: Programming Language :: Python
Classifier: Framework :: Odoo
Classifier: License :: OSI Approved :: GNU Affero General Public License v3
Classifier: Development Status :: 5 - Production/Stable
Requires-Python: >=3.5
Requires-Dist: odoo (<12.1dev,>=12.0a)
